idThree_classifier/__init__.py
idThree_classifier/idThree.py
idthree_classifier-0.1.1.dist-info/METADATA
idthree_classifier-0.1.1.dist-info/WHEEL
idthree_classifier-0.1.1.dist-info/top_level.txt
idthree_classifier-0.1.1.dist-info/RECORD
