Metadata-Version: 2.4
Name: idThree_classifier
Version: 0.1.1
Summary: A Python implementation of the ID3 decision tree algorithm
Home-page: https://github.com/yourusername/idThree-classifier
Author: Srinu Vakada
Author-email: your.email@example.com
Classifier: Programming Language :: Python :: 3
Classifier: License :: OSI Approved :: MIT License
Classifier: Operating System :: OS Independent
Requires-Python: >=3.6
Requires-Dist: pandas
Requires-Dist: numpy
Requires-Dist: graphviz
Dynamic: author
Dynamic: author-email
Dynamic: classifier
Dynamic: description
Dynamic: description-content-type
Dynamic: home-page
Dynamic: requires-dist
Dynamic: requires-python
Dynamic: summary
